myfigure/__init__.py
myfigure/myfigure.py
myfigure-1.0.1.dist-info/LICENSE
myfigure-1.0.1.dist-info/METADATA
myfigure-1.0.1.dist-info/WHEEL
myfigure-1.0.1.dist-info/top_level.txt
myfigure-1.0.1.dist-info/RECORD
