Metadata-Version: 2.1
Name: myfigure
Version: 1.0.1
Summary: standardized accessible plots
Author: Matteo Pecchi
License: MIT
Project-URL: Homepage, https://github.com/mpecchi/myfigure
Project-URL: Documentation, https://myfigure.readthedocs.io/en/latest/
Classifier: Programming Language :: Python :: 3
Classifier: License :: OSI Approved :: MIT License
Classifier: Operating System :: OS Independent
Requires-Python: >=3.10
License-File: LICENSE
Requires-Dist: numpy >=1.21.2
Requires-Dist: pandas >=1.3.3
Requires-Dist: matplotlib >=3.4.3
Requires-Dist: seaborn >=0.11.2
Requires-Dist: openpyxl
Requires-Dist: pyarrow
